greensim/__init__.py
greensim/logging.py
greensim/progress.py
greensim/random.py
greensim/tags.py
greensim-2.3.1.data/data/LICENSE
greensim-2.3.1.dist-info/LICENSE
greensim-2.3.1.dist-info/METADATA
greensim-2.3.1.dist-info/WHEEL
greensim-2.3.1.dist-info/top_level.txt
greensim-2.3.1.dist-info/RECORD
