Metadata-Version: 2.1
Name: greensim
Version: 2.3.1
Summary: Discrete event simulation toolkit based on greenlets
Home-page: https://github.com/ElementAI/greensim
Maintainer: Benoit Hamelin
Maintainer-email: ben@elementai.com
License: UNKNOWN
Platform: UNKNOWN
Classifier: Programming Language :: Python :: 3
Classifier: License :: OSI Approved :: MIT License
Classifier: Operating System :: OS Independent
Requires-Dist: greenlet (==0.4.14)
